combustache/__init__.py
combustache/__main__.py
combustache/__version__.py
combustache/ctx.py
combustache/exceptions.py
combustache/main.py
combustache/util.py
combustache/nodes/__init__.py
combustache/nodes/comment.py
combustache/nodes/delimiter.py
combustache/nodes/inheritance.py
combustache/nodes/interpolation.py
combustache/nodes/node.py
combustache/nodes/partial.py
combustache/nodes/section.py
combustache-3.0.1.dist-info/METADATA
combustache-3.0.1.dist-info/WHEEL
combustache-3.0.1.dist-info/entry_points.txt
combustache-3.0.1.dist-info/licenses/LICENSE
combustache-3.0.1.dist-info/RECORD
